main.py
molstar-0.0.0.dist-info/METADATA
molstar-0.0.0.dist-info/WHEEL
molstar-0.0.0.dist-info/top_level.txt
molstar-0.0.0.dist-info/RECORD
