Metadata-Version: 2.4
Name: molstar
Version: 0.0.0
Summary: placehold for future package
Requires-Python: >=3.10
